{
    "result": {
        "article": {
            "commentCount": 16,
            "contentElements": [],
            "contentHtml": "<div style=\"text-align: center;\"><span style=\"font-size: 18pt; font-family: 굴림;\"><font color=\"#ff0000\">◆</font><font color=\"#252525\">카페 첫 이벤트</font></span><span style=\"color: rgb(255, 0, 0); font-size: 18pt; font-family: 굴림;\">◆</span></div><div style=\"text-align: center;\"><br /></div><div style=\"text-align: justify;\"><span style=\"font-size: 12pt;\">&nbsp;<b>벌써 우리 카페가 게시글도 600을 넘고&nbsp;</b></span><b>인원도 220명을 넘었습니다!&nbsp;</b><b>(와~~)</b></div><div style=\"text-align: justify;\"><span style=\"font-size: 12pt;\"><b><br /></b></span></div><div style=\"text-align: justify;\"><span style=\"font-size: 16px;\"><b>그래서 소소하게 나마 이벤트를 하려고 합니다.</b></span></div><div style=\"text-align: justify;\"><span style=\"font-size: 10pt;\"><strike><font color=\"#767b86\">준비는 1도 하지 않았지만</font></strike></span><br /></div><div style=\"text-align: justify;\"><span style=\"font-size: 16px;\"><b><span style=\"font-size: 14pt;\">&nbsp;</span><br /></b></span></div><div style=\"text-align: center;\"><span style=\"font-size: 18.6667px;\"><b>-첫번째-</b></span></div><div style=\"text-align: center;\"><span style=\"font-size: 18.6667px;\"><b><br /></b></span></div><div style=\"text-align: justify;\"><span style=\"font-size: 18.6667px;\"><b>1천번째 게시글을 쓰신 멤버에게&nbsp;</b></span><b><u>문화상품권 5천원권</u>을 드리겠습니다.</b></div><div style=\"text-align: justify;\"><b>단,1천번째 게시글이 광고,도배,내용없는글일 경우 다음 게시글이 당첨됩니다.</b></div><div style=\"text-align: justify;\"><span style=\"font-size: 18.6667px;\"><b><strike><span style=\"font-size: 11pt;\">앞으로 400개 화이팅</span></strike></b></span></div><div style=\"text-align: justify;\"><br /></div><div style=\"text-align: justify;\"><br /></div><div style=\"text-align: center;\"><b>-두번째-</b></div><div style=\"text-align: center;\"><b><br /></b></div><div style=\"text-align: justify;\"><b>모바일 버전의 카페 디자인을&nbsp;</b><b>바꿀 필요가 있다고</b></div><div style=\"text-align: justify;\"><b>생각되어서&nbsp;</b><b>진행하게 된 이벤트입니다.</b></div><div style=\"text-align: center;\"><div style=\"text-align: justify; font-size: 13.3333px;\"><span style=\"font-size: 18.6667px;\"><b>모바일배너와 카페아이콘 대하여 <u>각각 문화상품권 5천원권</u>을 드립니다.</b></span></div><div style=\"text-align: justify; font-size: 13.3333px;\"><span style=\"font-size: 18.6667px;\"><b>&apos;카페 디자인 이벤트&apos; 게시판에 자신의 디자인을 뽐내주세요.</b></span></div></div><div style=\"text-align: justify;\"><br /></div><div style=\"text-align: center;\"><span style=\"font-size: 18.6667px;\"><b>①모바일 카페의 배너 디자인</b></span></div><div style=\"text-align: center;\"><span style=\"font-size: 18.6667px;\"><b>②카페 아이콘 디자인&nbsp; &nbsp; &nbsp; &nbsp;&nbsp;</b></span></div><div style=\"text-align: center;\"><span style=\"font-size: 18.6667px;\"><b><br /></b></span></div><div style=\"text-align: center;\"><span style=\"font-size: 18.6667px;\"><b>응모기간 : 2월 07일 ~ 2월 17일</b></span></div><div style=\"text-align: center;\"><span style=\"font-size: 18.6667px;\"><b>투표기간 : 2월 18일 ~ 2월 22일</b></span></div><div style=\"text-align: center;\"><span style=\"font-size: 18.6667px;\"><b><i><u>멤버투표점수 50% + 카페스탭투표점수 50% 로 결정됩니다.</u></i></b></span></div><div style=\"text-align: center;\"><br /></div><div style=\"text-align: center;\"><br /></div><div style=\"text-align: center;\"><b>-세번째-</b></div><div style=\"text-align: center;\"><b><br /></b></div><div style=\"text-align: justify;\"><b>봇카페인 만큼 소스관련 주제의 이벤트를 열어보려고 고심했습니다.<strike>..만</strike></b></div><div style=\"text-align: justify;\"><b><strike>아직 정해지지 않아서 추후 다시 공지하겠습니다.</strike></b></div><div style=\"text-align: justify;\"><b><strike>일단 상금만....</strike></b></div><div style=\"text-align: justify;\"><span style=\"font-size: 18.6667px;\"><b>주제는 Text RPG 입니다.</b></span></div><div style=\"text-align: justify;\"><span style=\"font-size: 18.6667px;\"><b>RPG 중에서도 아주 기초가 되는 두 가지에 한해서 소스를 작성하는 이벤트입니다.</b></span></div><div style=\"text-align: justify;\"><span style=\"font-size: 18.6667px;\"><b>RPG 게시판에 응모해주세요!</b></span></div><div style=\"text-align: justify;\"><span style=\"font-size: 18.6667px;\"><b><font color=\"#009e25\" style=\"\"><span style=\"font-size: 18pt;\">소스 공개를 원하지 않는 분은 저에게 쪽지 또는 메일로 보내주세요.</span></font></b></span></div><div style=\"text-align: justify;\"><span style=\"font-size: 18.6667px;\"><b><br /></b></span></div><div style=\"text-align: justify;\"><div style=\"font-size: 13.3333px; text-align: center;\"><span style=\"font-size: 18.6667px;\"><b>①로그인</b></span></div><div style=\"font-size: 13.3333px; text-align: center;\"><span style=\"font-size: 18.6667px;\"><b>②내정보</b></span></div><div style=\"font-size: 13.3333px; text-align: center;\"><span style=\"font-size: 18.6667px;\"><b><br /></b></span></div><div style=\"text-align: center;\"><span style=\"font-size: 18.6667px;\"><b>&lt;평가기준&gt;</b></span></div><div style=\"text-align: left;\"><span style=\"font-size: 18.6667px;\"><b>&nbsp; &nbsp; &nbsp; &nbsp; &nbsp; &nbsp; &nbsp; &nbsp; &nbsp; &nbsp; &nbsp; &nbsp; &nbsp; 소스의 직관성&nbsp; &nbsp; &nbsp; &nbsp; &nbsp; &nbsp; &nbsp; &nbsp; 1~10점</b></span></div><div style=\"text-align: left;\"><span style=\"font-size: 18.6667px;\"><b>&nbsp; &nbsp; &nbsp; &nbsp; &nbsp; &nbsp; &nbsp; &nbsp; &nbsp; &nbsp; &nbsp; &nbsp; &nbsp; 소스길이(공백제외)&nbsp; &nbsp; &nbsp; &nbsp; &nbsp;1~10점</b></span></div><div style=\"text-align: left;\"><span style=\"font-size: 18.6667px;\"><b>&nbsp; &nbsp; &nbsp; &nbsp; &nbsp; &nbsp; &nbsp; &nbsp; &nbsp; &nbsp; &nbsp; &nbsp; &nbsp; 중복코드사용&nbsp; &nbsp; &nbsp; &nbsp; &nbsp; &nbsp; 코드당 -1점</b></span></div><div style=\"text-align: left;\"><span style=\"font-size: 18.6667px;\"><b>&nbsp; &nbsp; &nbsp; &nbsp; &nbsp; &nbsp; &nbsp; &nbsp; &nbsp; &nbsp; &nbsp; &nbsp; &nbsp; 오류&nbsp; &nbsp; &nbsp; &nbsp; &nbsp; &nbsp; &nbsp; &nbsp; &nbsp; &nbsp; &nbsp; &nbsp; &nbsp; 개당 -2점</b></span></div><div style=\"text-align: left;\"><span style=\"font-size: 18.6667px;\"><b>&nbsp; &nbsp; &nbsp; &nbsp; &nbsp; &nbsp; &nbsp; &nbsp; &nbsp; &nbsp; &nbsp; &nbsp; &nbsp; 추가기능&nbsp; &nbsp; &nbsp; &nbsp; &nbsp; &nbsp; &nbsp; &nbsp; &nbsp; &nbsp; &nbsp; &nbsp; 0~5점</b></span></div><div style=\"text-align: left;\"><span style=\"font-size: 18.6667px;\"><b>&nbsp; &nbsp; &nbsp; &nbsp; &nbsp; &nbsp; &nbsp; &nbsp; &nbsp; &nbsp; &nbsp; &nbsp; &nbsp; 좋아요 3개이상일시&nbsp; &nbsp; &nbsp; &nbsp; &nbsp; &nbsp; +1점</b></span></div><div style=\"font-size: 13.3333px; text-align: center;\"><span style=\"font-size: 18.6667px;\"><b><br /></b></span></div><div style=\"font-size: 13.3333px; text-align: center;\"><b>최우수상 : 구글 기프트카드 1만원권</b></div><div style=\"font-size: 13.3333px; text-align: center;\"><b>창의성특별상 : 구글 기프트카드 5천원권</b><b>&nbsp; &nbsp;&nbsp;</b></div><div style=\"font-size: 13.3333px; text-align: center;\"><b>응모기간 : 2월 07일 ~ 2월 22일&nbsp; &nbsp;</b></div></div><div style=\"text-align: center;\"><b><br /></b></div>",
            "decorator": {
                "isPlug": false,
                "isShowSuicideSaver": false
            },
            "existScrapAddContent": false,
            "gdid": "90000004_01C2B33B000002B900000000",
            "id": 697,
            "isAutoSourcing": true,
            "isBlind": false,
            "isDeleteParent": false,
            "isEnableExternal": true,
            "isEnableScrap": true,
            "isEnableSocialPlugin": true,
            "isGroupPurchase": false,
            "isMarket": false,
            "isNewComment": false,
            "isNotice": false,
            "isOpen": true,
            "isPersonalTrade": false,
            "isReadable": true,
            "isWriteComment": true,
            "menu": {
                "badMenu": false,
                "badMenuByRestrict": false,
                "boardType": "L",
                "id": 24,
                "menuType": "B",
                "name": "| 이벤트 게시판 |"
            },
            "readCount": 245,
            "refArticleId": 697,
            "replyListOrder": "",
            "scrapCount": 0,
            "subject": "첫 이벤트! (수정)",
            "template": {
                "isUse": false
            },
            "writeDate": 1549511560707,
            "writer": {
                "id": "r960701",
                "image": {
                    "isAnimated": false,
                    "service": "BLOG",
                    "type": "c77_77",
                    "url": "https://blogpfthumb-phinf.pstatic.net/MjAxNjEyMTJfNDAg/MDAxNDgxNTQ2OTQ2NDg0.15o5AAoK0TP-pQ3aXXXRilfvCjaKPfwO_tnkFuGHhhMg.13qy0j5_J-XBxA2fUz4t8eZeC4isfCZxx9VQlIaGsR8g.PNG.r960701/20100515183900.png"
                },
                "memberLevelIconUrl": "https://cafe.pstatic.net/levelicon/1/13_150.gif",
                "memberLevelName": "챗봇 창시자",
                "nick": "카신"
            }
        },
        "articleId": 697,
        "attaches": [],
        "authority": {
            "isDoLike": true,
            "isEnableAttachFileDownload": true,
            "isHeadModifiable": false,
            "isModify": false,
            "isMove": false,
            "isRemove": false,
            "isReport": true,
            "isRightClick": true,
            "isSharable": true,
            "isShowLike": true,
            "isShowReply": false,
            "isShowStatistics": false,
            "isStore": false,
            "isWrite": true,
            "isWriteComment": true,
            "isWriteReply": true
        },
        "cafe": {
            "exposeReservation": false,
            "hasPopularArticle": true,
            "id": 29537083,
            "image": {
                "service": "CAFE",
                "type": "f100_100",
                "url": "https://mcafethumb-phinf.pstatic.net/MjAxOTAyMjVfMTg5/MDAxNTUxMDg2MDc1OTY2.umN5Kq9Z2sFRSdAXyJ2sz9UAlE0ofXm-dWJIRbeRbvsg.i_KxnwZ-FvDMQLnpo0ZYMo0Zl9JjOAPGWozW-WnLXJQg.PNG.wltjdqls5304/image.png"
            },
            "introduction": "자바스크립트를 사용하는 카카오톡 봇 관련 커뮤니티 입니다.",
            "isDormant": false,
            "memberCount": 5247,
            "name": "카카오톡 봇 커뮤니티",
            "openType": "O",
            "pcCafeName": "카카오톡 봇 커뮤니티",
            "url": "nameyee",
            "usingMemberLevel": true
        },
        "cafeId": 29537083,
        "comments": {
            "alarm": {
                "isChecked": false,
                "isShow": true
            },
            "disableWriteReason": "",
            "items": [
                {
                    "content": "와~~ 일단 글을 읽기 전에 댓글을 작성해봅니다(?)",
                    "id": 52634137,
                    "isArticleWriter": false,
                    "isDeleted": false,
                    "isNew": false,
                    "isRef": false,
                    "isRemovable": false,
                    "refId": 52634137,
                    "updateDate": 1549511737000,
                    "writer": {
                        "id": "jyworld04",
                        "image": {
                            "isAnimated": false,
                            "service": "CAFE",
                            "type": "c77_77",
                            "url": "https://cafethumb.pstatic.net/MjAxOTEwMTlfMjM3/MDAxNTcxNDczNzYwMzUx.7ea6qJQ6FV00nUnvOzEf0b13z0-4FIHX7Hv6n7gzf14g.W3TOOVxm7BhyRdHCWYud5hDSYyYJqZym8-RIF8f65zsg.PNG/%EC%BA%A1%EC%B2%98.PNG"
                        },
                        "nick": "민호"
                    }
                },
                {
                    "content": "와 이벤트를 진행하다니 참여하고 싶지만 디자인은 별로고 소스관련 이벤트는 미정이므로\r\n아직은 1천번째 게시물을 노려야겠군요(히익.. 나는 1천번째 게시물 못한ㄷ... 절대로...)",
                    "id": 52634242,
                    "isArticleWriter": false,
                    "isDeleted": false,
                    "isNew": false,
                    "isRef": true,
                    "isRemovable": false,
                    "refId": 52634137,
                    "updateDate": 1549511824000,
                    "writer": {
                        "id": "jyworld04",
                        "image": {
                            "isAnimated": false,
                            "service": "CAFE",
                            "type": "c77_77",
                            "url": "https://cafethumb.pstatic.net/MjAxOTEwMTlfMjM3/MDAxNTcxNDczNzYwMzUx.7ea6qJQ6FV00nUnvOzEf0b13z0-4FIHX7Hv6n7gzf14g.W3TOOVxm7BhyRdHCWYud5hDSYyYJqZym8-RIF8f65zsg.PNG/%EC%BA%A1%EC%B2%98.PNG"
                        },
                        "nick": "민호"
                    }
                },
                {
                    "content": "남은글 400개 미만!\r\n소스이벤은 문제를 낼지, 주제만 주고 자유소스를 받을지 고민중입니다. 어려우면 참가자가 적을테고\r\n쉬우면 대상자선정이 힘들테니....",
                    "id": 52635102,
                    "isArticleWriter": true,
                    "isDeleted": false,
                    "isNew": false,
                    "isRef": true,
                    "isRemovable": false,
                    "refId": 52634137,
                    "replyMember": {
                        "id": "jyworld04",
                        "nick": "민호"
                    },
                    "updateDate": 1549512534000,
                    "writer": {
                        "id": "r960701",
                        "image": {
                            "isAnimated": false,
                            "service": "BLOG",
                            "type": "c77_77",
                            "url": "https://blogpfthumb-phinf.pstatic.net/MjAxNjEyMTJfNDAg/MDAxNDgxNTQ2OTQ2NDg0.15o5AAoK0TP-pQ3aXXXRilfvCjaKPfwO_tnkFuGHhhMg.13qy0j5_J-XBxA2fUz4t8eZeC4isfCZxx9VQlIaGsR8g.PNG.r960701/20100515183900.png"
                        },
                        "nick": "카신"
                    }
                },
                {
                    "content": "상금은 사비로 충당하는거임?",
                    "id": 52640997,
                    "isArticleWriter": false,
                    "isDeleted": false,
                    "isNew": false,
                    "isRef": false,
                    "isRemovable": false,
                    "refId": 52640997,
                    "updateDate": 1549518389000,
                    "writer": {
                        "id": "astr36",
                        "image": {
                            "isAnimated": false,
                            "service": "BLOG",
                            "type": "c77_77",
                            "url": "https://blogpfthumb-phinf.pstatic.net/MjAxOTA3MTVfMjI5/MDAxNTYzMTg5NDIyNDM2.JHg7X32UJM4DC7JBBoSTmZpFed6r-v_aj0SdOOoFKlUg.nHWAX2DSUWTjVws1h3slnUKelTzec-ZGCewEEpZ3m-Ig.PNG.astr36/2048.png"
                        },
                        "nick": "Astro"
                    }
                },
                {
                    "content": "Yes,Sir",
                    "id": 52642222,
                    "isArticleWriter": true,
                    "isDeleted": false,
                    "isNew": false,
                    "isRef": true,
                    "isRemovable": false,
                    "refId": 52640997,
                    "updateDate": 1549519590000,
                    "writer": {
                        "id": "r960701",
                        "image": {
                            "isAnimated": false,
                            "service": "BLOG",
                            "type": "c77_77",
                            "url": "https://blogpfthumb-phinf.pstatic.net/MjAxNjEyMTJfNDAg/MDAxNDgxNTQ2OTQ2NDg0.15o5AAoK0TP-pQ3aXXXRilfvCjaKPfwO_tnkFuGHhhMg.13qy0j5_J-XBxA2fUz4t8eZeC4isfCZxx9VQlIaGsR8g.PNG.r960701/20100515183900.png"
                        },
                        "nick": "카신"
                    }
                },
                {
                    "content": "!",
                    "id": 52641681,
                    "isArticleWriter": false,
                    "isDeleted": false,
                    "isNew": false,
                    "isRef": false,
                    "isRemovable": false,
                    "refId": 52641681,
                    "updateDate": 1549519066000,
                    "writer": {
                        "id": "nenka",
                        "image": {
                            "isAnimated": false,
                            "service": "CAFE",
                            "type": "c77_77",
                            "url": "https://cafethumb.pstatic.net/MjAyMDA3MDhfMjgx/MDAxNTk0MTg2MDI4Mjk5.37YgO3GX_s_qBJW7QQlvROW9K3-N_TUmwyzij2PYHqsg.MS3dYQhDkB7GEv94vVp3EIvlAouKPTxKICZIW2kkMbcg.JPEG/externalFile.jpg"
                        },
                        "nick": "Nenka"
                    }
                },
                {
                    "content": "와...\r\n1번 : 귀찮다\r\n2번 : 곶아인\r\n3번 : 난 코딩못해!",
                    "id": 52652252,
                    "isArticleWriter": false,
                    "isDeleted": false,
                    "isNew": false,
                    "isRef": false,
                    "isRemovable": false,
                    "refId": 52652252,
                    "updateDate": 1549528575000,
                    "writer": {
                        "id": "qkralswo0825",
                        "image": {
                            "isAnimated": false,
                            "service": "BLOG",
                            "type": "c77_77",
                            "url": "https://blogpfthumb-phinf.pstatic.net/MjAxODA4MjdfNzIg/MDAxNTM1Mzc0ODA1Mzcx.4fPPQyRh3gNOuCLhi__tQWMyX0gkFf03Mq0wZ377BhMg.26O6HkEnB0ZHkJ9pjOGX0MI9p-bH9ONpRk6_3gROFPIg.PNG.qkralswo0825/profileImage.png"
                        },
                        "nick": "이름을입력해주세요"
                    }
                },
                {
                    "content": "사실 1~3 : 귀찮다 이신거 알고있어요",
                    "id": 52652979,
                    "isArticleWriter": true,
                    "isDeleted": false,
                    "isNew": false,
                    "isRef": true,
                    "isRemovable": false,
                    "refId": 52652252,
                    "updateDate": 1549529297000,
                    "writer": {
                        "id": "r960701",
                        "image": {
                            "isAnimated": false,
                            "service": "BLOG",
                            "type": "c77_77",
                            "url": "https://blogpfthumb-phinf.pstatic.net/MjAxNjEyMTJfNDAg/MDAxNDgxNTQ2OTQ2NDg0.15o5AAoK0TP-pQ3aXXXRilfvCjaKPfwO_tnkFuGHhhMg.13qy0j5_J-XBxA2fUz4t8eZeC4isfCZxx9VQlIaGsR8g.PNG.r960701/20100515183900.png"
                        },
                        "nick": "카신"
                    }
                },
                {
                    "content": "아닌데요!",
                    "id": 52653329,
                    "isArticleWriter": false,
                    "isDeleted": false,
                    "isNew": false,
                    "isRef": true,
                    "isRemovable": false,
                    "refId": 52652252,
                    "replyMember": {
                        "id": "r960701",
                        "nick": "카신"
                    },
                    "updateDate": 1549529722000,
                    "writer": {
                        "id": "qkralswo0825",
                        "image": {
                            "isAnimated": false,
                            "service": "BLOG",
                            "type": "c77_77",
                            "url": "https://blogpfthumb-phinf.pstatic.net/MjAxODA4MjdfNzIg/MDAxNTM1Mzc0ODA1Mzcx.4fPPQyRh3gNOuCLhi__tQWMyX0gkFf03Mq0wZ377BhMg.26O6HkEnB0ZHkJ9pjOGX0MI9p-bH9ONpRk6_3gROFPIg.PNG.qkralswo0825/profileImage.png"
                        },
                        "nick": "이름을입력해주세요"
                    }
                },
                {
                    "content": "그럼 1번 2번 동일인물이 둘다 타갈수 있나요?",
                    "id": 52675682,
                    "isArticleWriter": false,
                    "isDeleted": false,
                    "isNew": false,
                    "isRef": false,
                    "isRemovable": false,
                    "refId": 52675682,
                    "updateDate": 1549547388000,
                    "writer": {
                        "id": "starpia1209",
                        "image": {
                            "service": "CAFE",
                            "type": "c77_77",
                            "url": "https://ssl.pstatic.net/static/cafe/cafe_pc/default/cafe_profile_77.png"
                        },
                        "nick": "Starpia"
                    }
                }
            ],
            "last": {
                "id": 106365327,
                "refId": 106365327
            },
            "next": {
                "id": 52676288,
                "refId": 52675682
            }
        },
        "editorVersion": "LEGACY",
        "errorCode": null,
        "heads": [
            {
                "head": "투표",
                "headId": 40
            },
            {
                "head": "안내",
                "headId": 41
            },
            {
                "head": "신청",
                "headId": 42
            }
        ],
        "isReadOnlyMode": false,
        "isW800": false,
        "readOnlyModeInfo": {
            "emergency": false,
            "linkToNoticeURL": "https://section.cafe.naver.com/cafe-home/cafe-notice?noticeId=1650",
            "readOnlyNoticeDuration": "",
            "timeToNotice": false,
            "timeToPreNotice": false
        },
        "tags": []
    }
}